Metadata-Version: 2.1
Name: fastrandom
Version: 0.1.0
Summary: A shell tool to generate random bytes extremely fast e.g. for SSD scrubbing.
Home-page: http://github.com/Tronic/fastrandom
Author: L. Karkkainen
License: MIT
Platform: any
Classifier: Development Status :: 3 - Alpha
Classifier: Environment :: Console
Classifier: License :: OSI Approved :: MIT License
Classifier: Programming Language :: Python :: 3.8
Classifier: Programming Language :: Python :: 3.9
Requires-Python: >=3.8
